bot_net/bot_net.py
bot_net/requirements.txt
bot_net/app/env.py
bot_net/app/arguments/__init__.py
bot_net/app/arguments/input_arguments.py
bot_net/app/gui/manage.py
bot_net/app/gui/web/settings.py
bot_net/app/gui/web/urls.py
bot_net/app/gui/web/wsgi.py
bot_net/app/gui/web/bot_net/admin.py
bot_net/app/gui/web/bot_net/apps.py
bot_net/app/gui/web/bot_net/tests.py
bot_net/app/gui/web/bot_net/urls.py
bot_net/app/gui/web/bot_net/migrations/0001_initial.py
bot_net/app/gui/web/bot_net/migrations/0002_webparsingjobmodel.py
bot_net/app/gui/web/bot_net/migrations/0003_auto_20200129_1327.py
bot_net/app/gui/web/bot_net/migrations/0004_auto_20200129_1657.py
bot_net/app/gui/web/bot_net/migrations/0005_auto_20200129_1759.py
bot_net/app/gui/web/bot_net/migrations/0006_auto_20200129_1905.py
bot_net/app/gui/web/bot_net/migrations/0007_auto_20200129_2215.py
bot_net/app/gui/web/bot_net/migrations/0008_auto_20200203_1940.py
bot_net/app/gui/web/bot_net/models/__init__.py
bot_net/app/gui/web/bot_net/models/abstract_job_model.py
bot_net/app/gui/web/bot_net/models/abstract_model.py
bot_net/app/gui/web/bot_net/models/sniffing/__init__.py
bot_net/app/gui/web/bot_net/models/sniffing/sniffing_job_model.py
bot_net/app/gui/web/bot_net/models/web/__init__.py
bot_net/app/gui/web/bot_net/models/web/parsing/__init__.py
bot_net/app/gui/web/bot_net/models/web/parsing/web_parsing_job_model.py
bot_net/app/gui/web/bot_net/views/__init__.py
bot_net/app/gui/web/bot_net/views/abstract_job_view.py
bot_net/app/gui/web/bot_net/views/abstract_view.py
bot_net/app/gui/web/bot_net/views/index_view.py
bot_net/app/gui/web/bot_net/views/sql_view.py
bot_net/app/gui/web/bot_net/views/sniffing/__init__.py
bot_net/app/gui/web/bot_net/views/sniffing/abstract_sniffing_view.py
bot_net/app/gui/web/bot_net/views/sniffing/sniffing_view.py
bot_net/app/gui/web/bot_net/views/web/__init__.py
bot_net/app/gui/web/bot_net/views/web/parsing/__init__.py
bot_net/app/gui/web/bot_net/views/web/parsing/abstract_web_parsing_view.py
bot_net/egg-info/requirements.txt
bot_net-1.0.dist-info/LICENSE
bot_net-1.0.dist-info/METADATA
bot_net-1.0.dist-info/WHEEL
bot_net-1.0.dist-info/entry_points.txt
bot_net-1.0.dist-info/requirements.txt
bot_net-1.0.dist-info/top_level.txt
bot_net-1.0.dist-info/RECORD
