Metadata-Version: 2.1
Name: bot-net
Version: 1.0
Summary: Penetration testing tool
Home-page: UNKNOWN
Author: Abhay Chaudhary
License: UNKNOWN
Project-URL: Tracker, https://github.com/Abhayindia/BOT-NET
Project-URL: Source, https://github.com/Abhayindia/BOT-NET
Project-URL: Documentation, https://github.com/Abhayindia/BOT-NET
Keywords: bot_net penetration testing offensive cyber security pentest sniffing
Platform: UNKNOWN
Classifier: Programming Language :: Python :: 3
Classifier: License :: OSI Approved :: GNU General Public License v3 or later (GPLv3+)
Classifier: Operating System :: OS Independent
Classifier: Development Status :: 4 - Beta
Classifier: Environment :: Web Environment
Classifier: Natural Language :: English
Classifier: Topic :: Education :: Testing
Classifier: Topic :: Software Development :: Build Tools
Classifier: Topic :: System :: Clustering
Classifier: Topic :: System :: Monitoring
Classifier: Topic :: System :: Networking
Classifier: Topic :: System :: Hardware :: Symmetric Multi-processing
Classifier: Topic :: Utilities
Requires-Python: >=3.6
Requires-Dist: anytree
Requires-Dist: django
Requires-Dist: gunicorn
Requires-Dist: lxml
Requires-Dist: netifaces
Requires-Dist: numpy
Requires-Dist: pyshark
Requires-Dist: pytidylib
Requires-Dist: requests
Requires-Dist: simplejson
Requires-Dist: sqlmap
Requires-Dist: termcolor
Requires-Dist: urllib3
